{"trial_id": "13", "hyperparameters": {"space": [{"class_name": "Float", "config": {"name": "l2", "default": 1e-05, "conditions": [], "min_value": 1e-05, "max_value": 0.1, "step": null, "sampling": "log"}}, {"class_name": "Float", "config": {"name": "dropout", "default": 0.2, "conditions": [], "min_value": 0.2, "max_value": 0.5, "step": null, "sampling": "linear"}}, {"class_name": "Float", "config": {"name": "learning_rate", "default": 1e-06, "conditions": [], "min_value": 1e-06, "max_value": 0.01, "step": null, "sampling": "log"}}, {"class_name": "Float", "config": {"name": "clipnorm", "default": 0.5, "conditions": [], "min_value": 0.5, "max_value": 3.0, "step": null, "sampling": "linear"}}], "values": {"l2": 0.01492738542583107, "dropout": 0.2, "learning_rate": 0.00015740005509089068, "clipnorm": 1.1662540705844329}}, "metrics": {"metrics": {"accuracy": {"direction": "max", "observations": [{"value": [0.9840859770774841], "step": 21}]}, "loss": {"direction": "min", "observations": [{"value": [0.0666451696306467], "step": 21}]}, "val_accuracy": {"direction": "max", "observations": [{"value": [0.9708078801631927], "step": 21}]}, "val_loss": {"direction": "min", "observations": [{"value": [0.10246335342526436], "step": 21}]}, "learning_rate": {"direction": "min", "observations": [{"value": [0.0001574000489199534], "step": 21}]}}}, "score": 0.9708078801631927, "best_step": 21, "status": "COMPLETED", "message": null}